justpaste/__init__.py
justpaste/main.py
justpaste/settings.py
JustPaste.py-1.0.dist-info/LICENSE
JustPaste.py-1.0.dist-info/METADATA
JustPaste.py-1.0.dist-info/WHEEL
JustPaste.py-1.0.dist-info/top_level.txt
JustPaste.py-1.0.dist-info/RECORD
