Metadata-Version: 2.1
Name: JustPaste.py
Version: 1.0
Summary: A simple Python library for JustPaste.it API
Author-email: Devran Dogan <fidevran962@gmail.com>
Project-URL: Homepage, https://github.com/devdagoat/JustPaste.py
Classifier: Development Status :: 5 - Production/Stable
Classifier: Programming Language :: Python :: 3
Classifier: Topic :: Internet :: WWW/HTTP
Classifier: License :: OSI Approved :: GNU General Public License v3 or later (GPLv3+)
Classifier: Operating System :: OS Independent
Requires-Python: >=3.7
License-File: LICENSE
